{
  "id": "5610cc4c-bd37-4da7-848f-b1297a99d1bf",
  "prevId": "00000000-0000-0000-0000-000000000000",
  "version": "7",
  "dialect": "postgresql",
  "tables": {
    "public.documents": {
      "name": "documents",
      "schema": "",
      "columns": {
        "id": {
          "name": "id",
          "type": "serial",
          "primaryKey": true,
          "notNull": true
        },
        "user_id": {
          "name": "user_id",
          "type": "integer",
          "primaryKey": false,
          "notNull": true
        },
        "content": {
          "name": "content",
          "type": "text",
          "primaryKey": false,
          "notNull": true
        },
        "metadata": {
          "name": "metadata",
          "type": "jsonb",
          "primaryKey": false,
          "notNull": true
        },
        "keyword": {
          "name": "keyword",
          "type": "jsonb",
          "primaryKey": false,
          "notNull": false
        },
        "is_deleted": {
          "name": "is_deleted",
          "type": "boolean",
          "primaryKey": false,
          "notNull": false,
          "default": false
        },
        "is_favorite": {
          "name": "is_favorite",
          "type": "boolean",
          "primaryKey": false,
          "notNull": false,
          "default": false
        },
        "created_at": {
          "name": "created_at",
          "type": "timestamp",
          "primaryKey": false,
          "notNull": false,
          "default": "NOW()"
        },
        "updated_at": {
          "name": "updated_at",
          "type": "timestamp",
          "primaryKey": false,
          "notNull": false,
          "default": "NOW()"
        }
      },
      "indexes": {},
      "foreignKeys": {
        "documents_user_id_userss_id_fk": {
          "name": "documents_user_id_userss_id_fk",
          "tableFrom": "documents",
          "tableTo": "userss",
          "columnsFrom": [
            "user_id"
          ],
          "columnsTo": [
            "id"
          ],
          "onDelete": "no action",
          "onUpdate": "no action"
        }
      },
      "compositePrimaryKeys": {},
      "uniqueConstraints": {},
      "checkConstraints": {}
    },
    "public.payment": {
      "name": "payment",
      "schema": "",
      "columns": {
        "id": {
          "name": "id",
          "type": "serial",
          "primaryKey": false,
          "notNull": true
        },
        "order_id": {
          "name": "order_id",
          "type": "varchar",
          "primaryKey": false,
          "notNull": false
        },
        "status": {
          "name": "status",
          "type": "varchar",
          "primaryKey": false,
          "notNull": false,
          "default": "'pending'"
        },
        "user_id": {
          "name": "user_id",
          "type": "integer",
          "primaryKey": false,
          "notNull": false
        },
        "ref_id": {
          "name": "ref_id",
          "type": "integer",
          "primaryKey": false,
          "notNull": false
        },
        "method": {
          "name": "method",
          "type": "varchar",
          "primaryKey": false,
          "notNull": false
        },
        "credits": {
          "name": "credits",
          "type": "integer",
          "primaryKey": false,
          "notNull": false
        },
        "amount": {
          "name": "amount",
          "type": "integer",
          "primaryKey": false,
          "notNull": true
        },
        "created_at": {
          "name": "created_at",
          "type": "timestamp",
          "primaryKey": false,
          "notNull": false,
          "default": "now()"
        }
      },
      "indexes": {},
      "foreignKeys": {
        "payment_user_id_userss_id_fk": {
          "name": "payment_user_id_userss_id_fk",
          "tableFrom": "payment",
          "tableTo": "userss",
          "columnsFrom": [
            "user_id"
          ],
          "columnsTo": [
            "id"
          ],
          "onDelete": "no action",
          "onUpdate": "no action"
        }
      },
      "compositePrimaryKeys": {
        "payment_id_pk": {
          "name": "payment_id_pk",
          "columns": [
            "id"
          ]
        }
      },
      "uniqueConstraints": {},
      "checkConstraints": {}
    },
    "public.userss": {
      "name": "userss",
      "schema": "",
      "columns": {
        "id": {
          "name": "id",
          "type": "serial",
          "primaryKey": true,
          "notNull": true
        },
        "first_name": {
          "name": "first_name",
          "type": "varchar(255)",
          "primaryKey": false,
          "notNull": true
        },
        "last_name": {
          "name": "last_name",
          "type": "varchar(255)",
          "primaryKey": false,
          "notNull": true
        },
        "email": {
          "name": "email",
          "type": "varchar(255)",
          "primaryKey": false,
          "notNull": true
        },
        "phone_number": {
          "name": "phone_number",
          "type": "varchar(10)",
          "primaryKey": false,
          "notNull": true
        },
        "password": {
          "name": "password",
          "type": "varchar(255)",
          "primaryKey": false,
          "notNull": true
        },
        "credits": {
          "name": "credits",
          "type": "varchar",
          "primaryKey": false,
          "notNull": false,
          "default": "'10'"
        },
        "refresh_token": {
          "name": "refresh_token",
          "type": "text",
          "primaryKey": false,
          "notNull": false
        },
        "created_at": {
          "name": "created_at",
          "type": "timestamp",
          "primaryKey": false,
          "notNull": false,
          "default": "NOW()"
        },
        "updated_at": {
          "name": "updated_at",
          "type": "timestamp",
          "primaryKey": false,
          "notNull": false,
          "default": "NOW()"
        }
      },
      "indexes": {},
      "foreignKeys": {},
      "compositePrimaryKeys": {},
      "uniqueConstraints": {
        "userss_email_unique": {
          "name": "userss_email_unique",
          "nullsNotDistinct": false,
          "columns": [
            "email"
          ]
        }
      },
      "checkConstraints": {}
    }
  },
  "enums": {},
  "schemas": {},
  "sequences": {},
  "views": {},
  "_meta": {
    "columns": {},
    "schemas": {},
    "tables": {}
  }
}